Lua 在 5.0 前是基于栈的虚拟机，5.0 之后更改为基于寄存器的虚拟机（因此寄存器数量字段还是 `MaxStackSize` 😂）

Lua 指令集为定长指令集，每条指令 4 字节（32bit），其中 6bit 用于操作码，26bit 用于操作数，共 47 条指令
# 指令编码

Lua 编码模式有三种：`iABC`，`iABx`，`iAsBx`，`iAx`

`````col
````col-md
flexGrow=1
===
- `iABC`：携带 ABC 三个操作数，分别占用 8+9+9 bit，共 39 条
- `iABx`：携带 A、Bx 两个操作数，分别占用 8+18 bit，共 3 条
- `iAsBx`：携带 A、sBx 两个操作数，分别占用 8+18 bit，共 4 条
- `iAx`：只携带 1 个操作数，占用 26bit，有 1 条
````
````col-md
flexGrow=1
===
![[../../../_resources/images/指令集 2024-11-20 01.07.39.excalidraw]]
````
`````
## 操作码

从 0 到 46 共 47 条指令，声明一下即可，详见 [Lua 5.3 Bytecode Reference](https://the-ravi-programming-language.readthedocs.io/en/latest/lua_bytecode_reference.html#instruction-summary)
## 操作数

操作数大致可以分为 `A`，`OpArgN`，`OpArgU`，`OpArgR`，`OpArgK` 几种
- `A`：目标寄存器索引
- `OpArgN`：不使用，如 `MOVE` 的 C 操作数
- `OpArgR`：`iABC` 下表示寄存器索引，`iAsBx` 下表示跳转偏移
- `OpArgK`：`LOADK` 表示常量索引，`iABC` 模式表示常量索引或寄存器索引，最高位 1 表示常量索引
- `OpArgU`：布尔、整数、Upvalue 索引、子函数索引等
## 指令表

指令表结构体：

```go title:vm/opcodes.go
type opcode struct {
	testFlag byte
	setAFlag byte
	argBMode byte
	argCMode byte
	opMode   byte
	name     string
	action   func(Instruction, api.LuaVM)
}
```

为所有指令创建对应值即可

```go fold title:vm/opcodes.go
var opcodes = []opcode{
	{0, 1, OpArgR, OpArgN, IABC, "MOVE", move},
	{0, 1, OpArgK, OpArgN, IABx, "LOADK", loadK},
	{0, 1, OpArgN, OpArgN, IABx, "LOADKX", loadKx},
	{0, 1, OpArgU, OpArgU, IABC, "LOADBOOL", loadBool},
	{0, 1, OpArgU, OpArgN, IABC, "LOADNIL", loadNil},
	{0, 1, OpArgU, OpArgN, IABC, "GETUPVAL", getUpval},
	{0, 1, OpArgU, OpArgK, IABC, "GETTABUP", getTabUp},
	{0, 1, OpArgR, OpArgK, IABC, "GETTABLE", getTable},
	{0, 0, OpArgK, OpArgK, IABC, "SETTABUP", setTabUp},
	{0, 0, OpArgU, OpArgN, IABC, "SETUPVAL", setUpval},
	{0, 0, OpArgK, OpArgK, IABC, "SETTABLE", setTable},
	{0, 1, OpArgU, OpArgU, IABC, "NEWTABLE", newTable},
	{0, 1, OpArgR, OpArgK, IABC, "SELF", self},
	{0, 1, OpArgK, OpArgK, IABC, "ADD", add},
	{0, 1, OpArgK, OpArgK, IABC, "SUB", sub},
	{0, 1, OpArgK, OpArgK, IABC, "MUL", mul},
	{0, 1, OpArgK, OpArgK, IABC, "MOD", mod},
	{0, 1, OpArgK, OpArgK, IABC, "POW", pow},
	{0, 1, OpArgK, OpArgK, IABC, "DIV", div},
	{0, 1, OpArgK, OpArgK, IABC, "IDIV", idiv},
	{0, 1, OpArgK, OpArgK, IABC, "BAND", band},
	{0, 1, OpArgK, OpArgK, IABC, "BOR", bor},
	{0, 1, OpArgK, OpArgK, IABC, "BXOR", bxor},
	{0, 1, OpArgK, OpArgK, IABC, "SHL", shl},
	{0, 1, OpArgK, OpArgK, IABC, "SHR", shr},
	{0, 1, OpArgR, OpArgN, IABC, "UNM", unm},
	{0, 1, OpArgR, OpArgN, IABC, "BNOT", bnot},
	{0, 1, OpArgR, OpArgN, IABC, "NOT", not},
	{0, 1, OpArgR, OpArgN, IABC, "LEN", length},
	{0, 1, OpArgR, OpArgR, IABC, "CONCAT", concat},
	{0, 0, OpArgR, OpArgN, IAsBx, "JMP", jmp},
	{1, 0, OpArgK, OpArgK, IABC, "EQ", eq},
	{1, 0, OpArgK, OpArgK, IABC, "LT", lt},
	{1, 0, OpArgK, OpArgK, IABC, "LE", le},
	{1, 0, OpArgN, OpArgU, IABC, "TEST", test},
	{1, 1, OpArgR, OpArgU, IABC, "TESTSET", testSet},
	{0, 1, OpArgU, OpArgU, IABC, "CALL", call},
	{0, 1, OpArgU, OpArgU, IABC, "TAILCALL", tailcall},
	{0, 0, OpArgU, OpArgN, IABC, "RETURN", lua_return},
	{0, 1, OpArgR, OpArgN, IAsBx, "FORLOOP", forLoop},
	{0, 1, OpArgR, OpArgN, IAsBx, "FORPREP", forPrep},
	{0, 0, OpArgN, OpArgU, IABC, "TFORCALL", tForCall},
	{0, 1, OpArgR, OpArgN, IAsBx, "TFORLOOP", tForLoop},
	{0, 0, OpArgU, OpArgU, IABC, "SETLIST", setList},
	{0, 1, OpArgU, OpArgN, IABx, "CLOSURE", closure},
	{0, 1, OpArgU, OpArgN, IABC, "VARARG", vararg},
	{0, 0, OpArgU, OpArgU, IAx, "EXTRAARG", nil},
}
```
# 指令解码

创建 `uint32` 别名 `Instruction`，并为其创建参数提取方法

```go title:vm/instruction.go
type Instruction uint32

const MAXARG_Bx = 1<<18 - 1
const MAXARG_sBx = MAXARG_Bx >> 1

func (self Instruction) ABC() (a, b, c int) {
	a = int(self >> 6 & 0xFF)
	c = int(self >> 14 & 0x1FF)
	b = int(self >> 23 & 0x1FF)
	return
}

func (self Instruction) ABx() (a, bx int) {
	a = int(self >> 6 & 0xFF)
	bx = int(self >> 14)
	return
}

func (self Instruction) AsBx() (a, sbx int) {
	a, bx := self.ABx()
	return a, bx - MAXARG_sBx
}

func (self Instruction) Ax() int {
	return int(self >> 6)
}
```

>[!note] AsBx 方法：偏移二进制码编码模式
> Offset Binary，又称 Excess-K。当 `sBx` 解释成无符号整型时为 `x`，则解释成有符号整型时为 `x-K`，`K` 为 `sBx` 类型可取最大值的一半，即 `MAXARG_sBx `
